.gitignore
MANIFEST.in
README.txt
setup.cfg
setup.py
collective/__init__.py
collective.slideshow.egg-info/PKG-INFO
collective.slideshow.egg-info/SOURCES.txt
collective.slideshow.egg-info/dependency_links.txt
collective.slideshow.egg-info/entry_points.txt
collective.slideshow.egg-info/namespace_packages.txt
collective.slideshow.egg-info/not-zip-safe
collective.slideshow.egg-info/paster_plugins.txt
collective.slideshow.egg-info/requires.txt
collective.slideshow.egg-info/top_level.txt
collective/slideshow/__init__.py
collective/slideshow/adapters.py
collective/slideshow/configure.zcml
collective/slideshow/events.py
collective/slideshow/indexers.py
collective/slideshow/interfaces.py
collective/slideshow/setuphandlers.py
collective/slideshow/tests.py
collective/slideshow/browser/__init__.py
collective/slideshow/browser/configure.zcml
collective/slideshow/browser/views.py
collective/slideshow/browser/templates/slideshowListing.pt
collective/slideshow/browser/templates/slideshow_item.pt
collective/slideshow/profiles/default/browserlayer.xml
collective/slideshow/profiles/default/catalog.xml
collective/slideshow/profiles/default/collective_slideshow-default.txt
collective/slideshow/profiles/default/metadata.xml
collective/slideshow/profiles/default/registry.xml
docs/HISTORY.txt
docs/INSTALL.txt
docs/LICENSE.GPL
docs/LICENSE.txt