Metadata-Version: 1.1
Name: collective.slideshow
Version: 0.0.2
Summary: Adds slideshow folder to all folderish items.
Home-page: https://github.com/intk/collective.slideshow
Author: Andre Goncalves
Author-email: andre@intk.com
License: GPL
Download-URL: https://github.com/intk/collective.slideshow/tarball/0.0.1
Keywords: slideshow
Platform: UNKNOWN
Classifier: Framework :: Plone
Classifier: Programming Language :: Python
